MANIFEST.in
README.md
setup.py
wormcat_batch/create_sunburst.py
wormcat_batch/create_wormcat_xlsx.py
wormcat_batch/execute_r.py
wormcat_batch/is_wormcat_installed.R
wormcat_batch/run_wormcat_batch.py
wormcat_batch/sunburst.template
wormcat_batch/worm_cat.R
wormcat_batch.egg-info/PKG-INFO
wormcat_batch.egg-info/SOURCES.txt
wormcat_batch.egg-info/dependency_links.txt
wormcat_batch.egg-info/entry_points.txt
wormcat_batch.egg-info/not-zip-safe
wormcat_batch.egg-info/requires.txt
wormcat_batch.egg-info/top_level.txt