Metadata-Version: 2.1
Name: wormcat-batch
Version: 1.1.10
Summary: Batch processing for Wormcat data
Home-page: https://github.com/dphiggs01/Wormcat_batch
Author: Dan Higgins
Author-email: daniel.higgins@yahoo.com
License: MIT
